[
  {
    "id": 1,
    "customerId": 5513,
    "customerName": "Customer 5513",
    "insightType": "Churn Prevention",
    "category": "Revenue Growth",
    "description": "Automated CRM insight generated based on recent customer behavior and transaction patterns.",
    "priority": 2,
    "recommendedAction": "Offer digital banking feature walkthrough",
    "potentialRevenue": 42310.39,
    "riskExposure": 0.16,
    "generatedAt": "2024-02-23T12:00:00Z",
    "status": "In Progress",
    "assignedTo": "Daniel Lee",
    "relatedAlerts": []
  },
  {
    "id": 2,
    "customerId": 9383,
    "customerName": "Customer 9383",
    "insightType": "Up-Sell Opportunity",
    "category": "Customer Experience",
    "description": "Automated CRM insight generated based on recent customer behavior and transaction patterns.",
    "priority": 4,
    "recommendedAction": "Offer digital banking feature walkthrough",
    "potentialRevenue": 23186.13,
    "riskExposure": 0.78,
    "generatedAt": "2024-02-25T00:00:00Z",
    "status": "In Progress",
    "assignedTo": "Amit Sharma",
    "relatedAlerts": []
  },
  {
    "id": 3,
    "customerId": 6624,
    "customerName": "Customer 6624",
    "insightType": "Retention Risk",
    "category": "Revenue Growth",
    "description": "Automated CRM insight generated based on recent customer behavior and transaction patterns.",
    "priority": 5,
    "recommendedAction": "Offer digital banking feature walkthrough",
    "potentialRevenue": 38506.69,
    "riskExposure": 0.76,
    "generatedAt": "2024-02-03T21:00:00Z",
    "status": "In Progress",
    "assignedTo": "Daniel Lee",
    "relatedAlerts": []
  },
  {
    "id": 4,
    "customerId": 2248,
    "customerName": "Customer 2248",
    "insightType": "Up-Sell Opportunity",
    "category": "Customer Retention",
    "description": "Automated CRM insight generated based on recent customer behavior and transaction patterns.",
    "priority": 4,
    "recommendedAction": "Provide loyalty benefits to improve retention",
    "potentialRevenue": 17176.08,
    "riskExposure": 0.81,
    "generatedAt": "2024-02-02T06:00:00Z",
    "status": "In Progress",
    "assignedTo": "Emily Clark",
    "relatedAlerts": []
  },
  {
    "id": 5,
    "customerId": 2698,
    "customerName": "Customer 2698",
    "insightType": "Retention Risk",
    "category": "Customer Experience",
    "description": "Automated CRM insight generated based on recent customer behavior and transaction patterns.",
    "priority": 2,
    "recommendedAction": "Offer digital banking feature walkthrough",
    "potentialRevenue": 46383.38,
    "riskExposure": 0.08,
    "generatedAt": "2024-02-24T08:00:00Z",
    "status": "Closed",
    "assignedTo": "Michael Brown",
    "relatedAlerts": []
  },
  {
    "id": 6,
    "customerId": 9964,
    "customerName": "Customer 9964",
    "insightType": "Cross-Sell Opportunity",
    "category": "Customer Retention",
    "description": "Automated CRM insight generated based on recent customer behavior and transaction patterns.",
    "priority": 3,
    "recommendedAction": "Provide loyalty benefits to improve retention",
    "potentialRevenue": 14450.0,
    "riskExposure": 0.46,
    "generatedAt": "2024-02-16T16:00:00Z",
    "status": "Closed",
    "assignedTo": "Emily Clark",
    "relatedAlerts": []
  },
  {
    "id": 7,
    "customerId": 9787,
    "customerName": "Customer 9787",
    "insightType": "Retention Risk",
    "category": "Risk Mitigation",
    "description": "Automated CRM insight generated based on recent customer behavior and transaction patterns.",
    "priority": 3,
    "recommendedAction": "Recommend credit card upgrade with higher limits",
    "potentialRevenue": 20780.8,
    "riskExposure": 0.72,
    "generatedAt": "2024-02-21T07:00:00Z",
    "status": "Closed",
    "assignedTo": "Emily Clark",
    "relatedAlerts": []
  },
  {
    "id": 8,
    "customerId": 9820,
    "customerName": "Customer 9820",
    "insightType": "Customer Engagement",
    "category": "Risk Mitigation",
    "description": "Automated CRM insight generated based on recent customer behavior and transaction patterns.",
    "priority": 4,
    "recommendedAction": "Introduce bundled banking products",
    "potentialRevenue": 18387.06,
    "riskExposure": 0.8,
    "generatedAt": "2024-02-27T13:00:00Z",
    "status": "Open",
    "assignedTo": "Sarah Johnson",
    "relatedAlerts": []
  },
  {
    "id": 9,
    "customerId": 2651,
    "customerName": "Customer 2651",
    "insightType": "Product Recommendation",
    "category": "Customer Experience",
    "description": "Automated CRM insight generated based on recent customer behavior and transaction patterns.",
    "priority": 4,
    "recommendedAction": "Recommend credit card upgrade with higher limits",
    "potentialRevenue": 36149.38,
    "riskExposure": 0.73,
    "generatedAt": "2024-02-03T10:00:00Z",
    "status": "In Progress",
    "assignedTo": "Priya Patel",
    "relatedAlerts": []
  },
  {
    "id": 10,
    "customerId": 1330,
    "customerName": "Customer 1330",
    "insightType": "Retention Risk",
    "category": "Revenue Growth",
    "description": "Automated CRM insight generated based on recent customer behavior and transaction patterns.",
    "priority": 4,
    "recommendedAction": "Introduce bundled banking products",
    "potentialRevenue": 8997.61,
    "riskExposure": 0.67,
    "generatedAt": "2024-02-12T09:00:00Z",
    "status": "Closed",
    "assignedTo": "Amit Sharma",
    "relatedAlerts": []
  },
  {
    "id": 11,
    "customerId": 9037,
    "customerName": "Customer 9037",
    "insightType": "Customer Engagement",
    "category": "Revenue Growth",
    "description": "Automated CRM insight generated based on recent customer behavior and transaction patterns.",
    "priority": 4,
    "recommendedAction": "Introduce bundled banking products",
    "potentialRevenue": 23632.14,
    "riskExposure": 0.61,
    "generatedAt": "2024-02-10T08:00:00Z",
    "status": "Open",
    "assignedTo": "Michael Brown",
    "relatedAlerts": []
  },
  {
    "id": 12,
    "customerId": 5876,
    "customerName": "Customer 5876",
    "insightType": "Up-Sell Opportunity",
    "category": "Revenue Growth",
    "description": "Automated CRM insight generated based on recent customer behavior and transaction patterns.",
    "priority": 1,
    "recommendedAction": "Offer premium investment portfolio management services",
    "potentialRevenue": 42561.79,
    "riskExposure": 0.48,
    "generatedAt": "2024-02-26T07:00:00Z",
    "status": "Open",
    "assignedTo": "Michael Brown",
    "relatedAlerts": []
  },
  {
    "id": 13,
    "customerId": 4119,
    "customerName": "Customer 4119",
    "insightType": "Cross-Sell Opportunity",
    "category": "Customer Retention",
    "description": "Automated CRM insight generated based on recent customer behavior and transaction patterns.",
    "priority": 1,
    "recommendedAction": "Recommend credit card upgrade with higher limits",
    "potentialRevenue": 48477.24,
    "riskExposure": 0.44,
    "generatedAt": "2024-02-01T17:00:00Z",
    "status": "Closed",
    "assignedTo": "Sarah Johnson",
    "relatedAlerts": []
  },
  {
    "id": 14,
    "customerId": 9518,
    "customerName": "Customer 9518",
    "insightType": "Customer Engagement",
    "category": "Customer Experience",
    "description": "Automated CRM insight generated based on recent customer behavior and transaction patterns.",
    "priority": 4,
    "recommendedAction": "Offer digital banking feature walkthrough",
    "potentialRevenue": 25828.96,
    "riskExposure": 0.63,
    "generatedAt": "2024-02-20T16:00:00Z",
    "status": "Closed",
    "assignedTo": "Michael Brown",
    "relatedAlerts": []
  },
  {
    "id": 15,
    "customerId": 1007,
    "customerName": "Customer 1007",
    "insightType": "Retention Risk",
    "category": "Customer Retention",
    "description": "Automated CRM insight generated based on recent customer behavior and transaction patterns.",
    "priority": 5,
    "recommendedAction": "Recommend credit card upgrade with higher limits",
    "potentialRevenue": 11172.19,
    "riskExposure": 0.14,
    "generatedAt": "2024-02-11T02:00:00Z",
    "status": "Open",
    "assignedTo": "Sarah Johnson",
    "relatedAlerts": []
  },
  {
    "id": 16,
    "customerId": 1614,
    "customerName": "Customer 1614",
    "insightType": "Cross-Sell Opportunity",
    "category": "Customer Retention",
    "description": "Automated CRM insight generated based on recent customer behavior and transaction patterns.",
    "priority": 2,
    "recommendedAction": "Introduce bundled banking products",
    "potentialRevenue": 32565.88,
    "riskExposure": 0.54,
    "generatedAt": "2024-02-10T23:00:00Z",
    "status": "Closed",
    "assignedTo": "Emily Clark",
    "relatedAlerts": []
  },
  {
    "id": 17,
    "customerId": 3605,
    "customerName": "Customer 3605",
    "insightType": "Cross-Sell Opportunity",
    "category": "Customer Retention",
    "description": "Automated CRM insight generated based on recent customer behavior and transaction patterns.",
    "priority": 2,
    "recommendedAction": "Recommend credit card upgrade with higher limits",
    "potentialRevenue": 30150.36,
    "riskExposure": 0.89,
    "generatedAt": "2024-02-26T15:00:00Z",
    "status": "Closed",
    "assignedTo": "Michael Brown",
    "relatedAlerts": []
  },
  {
    "id": 18,
    "customerId": 9105,
    "customerName": "Customer 9105",
    "insightType": "Up-Sell Opportunity",
    "category": "Risk Mitigation",
    "description": "Automated CRM insight generated based on recent customer behavior and transaction patterns.",
    "priority": 4,
    "recommendedAction": "Schedule personalized financial advisory session",
    "potentialRevenue": 15249.9,
    "riskExposure": 0.43,
    "generatedAt": "2024-02-01T07:00:00Z",
    "status": "In Progress",
    "assignedTo": "Sarah Johnson",
    "relatedAlerts": []
  },
  {
    "id": 19,
    "customerId": 8246,
    "customerName": "Customer 8246",
    "insightType": "Product Recommendation",
    "category": "Customer Experience",
    "description": "Automated CRM insight generated based on recent customer behavior and transaction patterns.",
    "priority": 3,
    "recommendedAction": "Offer premium investment portfolio management services",
    "potentialRevenue": 32364.93,
    "riskExposure": 0.51,
    "generatedAt": "2024-02-08T11:00:00Z",
    "status": "Open",
    "assignedTo": "Priya Patel",
    "relatedAlerts": []
  },
  {
    "id": 20,
    "customerId": 3507,
    "customerName": "Customer 3507",
    "insightType": "Cross-Sell Opportunity",
    "category": "Customer Retention",
    "description": "Automated CRM insight generated based on recent customer behavior and transaction patterns.",
    "priority": 5,
    "recommendedAction": "Offer premium investment portfolio management services",
    "potentialRevenue": 19148.39,
    "riskExposure": 0.4,
    "generatedAt": "2024-02-15T14:00:00Z",
    "status": "In Progress",
    "assignedTo": "Daniel Lee",
    "relatedAlerts": []
  },
  {
    "id": 21,
    "customerId": 5796,
    "customerName": "Customer 5796",
    "insightType": "Up-Sell Opportunity",
    "category": "Risk Mitigation",
    "description": "Automated CRM insight generated based on recent customer behavior and transaction patterns.",
    "priority": 2,
    "recommendedAction": "Offer premium investment portfolio management services",
    "potentialRevenue": 41933.25,
    "riskExposure": 0.52,
    "generatedAt": "2024-02-26T17:00:00Z",
    "status": "Closed",
    "assignedTo": "Emily Clark",
    "relatedAlerts": []
  },
  {
    "id": 22,
    "customerId": 5285,
    "customerName": "Customer 5285",
    "insightType": "Product Recommendation",
    "category": "Customer Experience",
    "description": "Automated CRM insight generated based on recent customer behavior and transaction patterns.",
    "priority": 3,
    "recommendedAction": "Recommend credit card upgrade with higher limits",
    "potentialRevenue": 14133.25,
    "riskExposure": 0.57,
    "generatedAt": "2024-02-07T16:00:00Z",
    "status": "In Progress",
    "assignedTo": "Emily Clark",
    "relatedAlerts": []
  },
  {
    "id": 23,
    "customerId": 3380,
    "customerName": "Customer 3380",
    "insightType": "Cross-Sell Opportunity",
    "category": "Customer Retention",
    "description": "Automated CRM insight generated based on recent customer behavior and transaction patterns.",
    "priority": 5,
    "recommendedAction": "Introduce bundled banking products",
    "potentialRevenue": 31310.03,
    "riskExposure": 0.8,
    "generatedAt": "2024-02-05T12:00:00Z",
    "status": "In Progress",
    "assignedTo": "Michael Brown",
    "relatedAlerts": []
  },
  {
    "id": 24,
    "customerId": 9933,
    "customerName": "Customer 9933",
    "insightType": "Retention Risk",
    "category": "Customer Retention",
    "description": "Automated CRM insight generated based on recent customer behavior and transaction patterns.",
    "priority": 5,
    "recommendedAction": "Recommend credit card upgrade with higher limits",
    "potentialRevenue": 13058.06,
    "riskExposure": 0.54,
    "generatedAt": "2024-02-18T23:00:00Z",
    "status": "Closed",
    "assignedTo": "Michael Brown",
    "relatedAlerts": []
  },
  {
    "id": 25,
    "customerId": 9089,
    "customerName": "Customer 9089",
    "insightType": "Product Recommendation",
    "category": "Revenue Growth",
    "description": "Automated CRM insight generated based on recent customer behavior and transaction patterns.",
    "priority": 4,
    "recommendedAction": "Schedule personalized financial advisory session",
    "potentialRevenue": 30828.8,
    "riskExposure": 0.21,
    "generatedAt": "2024-02-11T05:00:00Z",
    "status": "In Progress",
    "assignedTo": "Priya Patel",
    "relatedAlerts": []
  },
  {
    "id": 26,
    "customerId": 4593,
    "customerName": "Customer 4593",
    "insightType": "Product Recommendation",
    "category": "Revenue Growth",
    "description": "Automated CRM insight generated based on recent customer behavior and transaction patterns.",
    "priority": 3,
    "recommendedAction": "Offer digital banking feature walkthrough",
    "potentialRevenue": 42385.34,
    "riskExposure": 0.71,
    "generatedAt": "2024-02-07T15:00:00Z",
    "status": "Open",
    "assignedTo": "Emily Clark",
    "relatedAlerts": []
  },
  {
    "id": 27,
    "customerId": 3817,
    "customerName": "Customer 3817",
    "insightType": "Churn Prevention",
    "category": "Risk Mitigation",
    "description": "Automated CRM insight generated based on recent customer behavior and transaction patterns.",
    "priority": 5,
    "recommendedAction": "Recommend credit card upgrade with higher limits",
    "potentialRevenue": 27338.48,
    "riskExposure": 0.67,
    "generatedAt": "2024-02-03T16:00:00Z",
    "status": "Open",
    "assignedTo": "Sarah Johnson",
    "relatedAlerts": []
  },
  {
    "id": 28,
    "customerId": 4340,
    "customerName": "Customer 4340",
    "insightType": "Retention Risk",
    "category": "Risk Mitigation",
    "description": "Automated CRM insight generated based on recent customer behavior and transaction patterns.",
    "priority": 4,
    "recommendedAction": "Recommend credit card upgrade with higher limits",
    "potentialRevenue": 43370.85,
    "riskExposure": 0.69,
    "generatedAt": "2024-02-12T19:00:00Z",
    "status": "Closed",
    "assignedTo": "Sarah Johnson",
    "relatedAlerts": []
  },
  {
    "id": 29,
    "customerId": 2578,
    "customerName": "Customer 2578",
    "insightType": "Up-Sell Opportunity",
    "category": "Risk Mitigation",
    "description": "Automated CRM insight generated based on recent customer behavior and transaction patterns.",
    "priority": 4,
    "recommendedAction": "Recommend credit card upgrade with higher limits",
    "potentialRevenue": 46470.99,
    "riskExposure": 0.56,
    "generatedAt": "2024-02-08T13:00:00Z",
    "status": "Closed",
    "assignedTo": "Emily Clark",
    "relatedAlerts": []
  },
  {
    "id": 30,
    "customerId": 4201,
    "customerName": "Customer 4201",
    "insightType": "Churn Prevention",
    "category": "Revenue Growth",
    "description": "Automated CRM insight generated based on recent customer behavior and transaction patterns.",
    "priority": 2,
    "recommendedAction": "Provide loyalty benefits to improve retention",
    "potentialRevenue": 13141.9,
    "riskExposure": 0.72,
    "generatedAt": "2024-02-24T19:00:00Z",
    "status": "Closed",
    "assignedTo": "Emily Clark",
    "relatedAlerts": []
  },
  {
    "id": 31,
    "customerId": 8263,
    "customerName": "Customer 8263",
    "insightType": "Retention Risk",
    "category": "Customer Retention",
    "description": "Automated CRM insight generated based on recent customer behavior and transaction patterns.",
    "priority": 3,
    "recommendedAction": "Offer premium investment portfolio management services",
    "potentialRevenue": 8817.25,
    "riskExposure": 0.0,
    "generatedAt": "2024-02-26T13:00:00Z",
    "status": "Open",
    "assignedTo": "Sarah Johnson",
    "relatedAlerts": []
  },
  {
    "id": 32,
    "customerId": 8705,
    "customerName": "Customer 8705",
    "insightType": "Up-Sell Opportunity",
    "category": "Customer Experience",
    "description": "Automated CRM insight generated based on recent customer behavior and transaction patterns.",
    "priority": 2,
    "recommendedAction": "Recommend credit card upgrade with higher limits",
    "potentialRevenue": 39608.64,
    "riskExposure": 0.13,
    "generatedAt": "2024-02-25T13:00:00Z",
    "status": "Closed",
    "assignedTo": "Amit Sharma",
    "relatedAlerts": []
  },
  {
    "id": 33,
    "customerId": 8120,
    "customerName": "Customer 8120",
    "insightType": "Product Recommendation",
    "category": "Customer Experience",
    "description": "Automated CRM insight generated based on recent customer behavior and transaction patterns.",
    "priority": 1,
    "recommendedAction": "Provide loyalty benefits to improve retention",
    "potentialRevenue": 3565.75,
    "riskExposure": 0.56,
    "generatedAt": "2024-02-04T23:00:00Z",
    "status": "In Progress",
    "assignedTo": "Daniel Lee",
    "relatedAlerts": []
  },
  {
    "id": 34,
    "customerId": 5979,
    "customerName": "Customer 5979",
    "insightType": "Cross-Sell Opportunity",
    "category": "Customer Experience",
    "description": "Automated CRM insight generated based on recent customer behavior and transaction patterns.",
    "priority": 1,
    "recommendedAction": "Recommend credit card upgrade with higher limits",
    "potentialRevenue": 22825.98,
    "riskExposure": 0.35,
    "generatedAt": "2024-02-20T19:00:00Z",
    "status": "Open",
    "assignedTo": "Emily Clark",
    "relatedAlerts": []
  },
  {
    "id": 35,
    "customerId": 6902,
    "customerName": "Customer 6902",
    "insightType": "Churn Prevention",
    "category": "Customer Retention",
    "description": "Automated CRM insight generated based on recent customer behavior and transaction patterns.",
    "priority": 5,
    "recommendedAction": "Provide loyalty benefits to improve retention",
    "potentialRevenue": 44563.47,
    "riskExposure": 0.89,
    "generatedAt": "2024-02-26T20:00:00Z",
    "status": "In Progress",
    "assignedTo": "Michael Brown",
    "relatedAlerts": []
  },
  {
    "id": 36,
    "customerId": 6430,
    "customerName": "Customer 6430",
    "insightType": "Churn Prevention",
    "category": "Risk Mitigation",
    "description": "Automated CRM insight generated based on recent customer behavior and transaction patterns.",
    "priority": 3,
    "recommendedAction": "Offer digital banking feature walkthrough",
    "potentialRevenue": 29728.9,
    "riskExposure": 0.53,
    "generatedAt": "2024-02-12T03:00:00Z",
    "status": "Closed",
    "assignedTo": "Emily Clark",
    "relatedAlerts": []
  },
  {
    "id": 37,
    "customerId": 3942,
    "customerName": "Customer 3942",
    "insightType": "Up-Sell Opportunity",
    "category": "Customer Retention",
    "description": "Automated CRM insight generated based on recent customer behavior and transaction patterns.",
    "priority": 2,
    "recommendedAction": "Offer digital banking feature walkthrough",
    "potentialRevenue": 18935.97,
    "riskExposure": 0.3,
    "generatedAt": "2024-02-23T17:00:00Z",
    "status": "Open",
    "assignedTo": "Amit Sharma",
    "relatedAlerts": []
  },
  {
    "id": 38,
    "customerId": 1564,
    "customerName": "Customer 1564",
    "insightType": "Cross-Sell Opportunity",
    "category": "Risk Mitigation",
    "description": "Automated CRM insight generated based on recent customer behavior and transaction patterns.",
    "priority": 4,
    "recommendedAction": "Recommend credit card upgrade with higher limits",
    "potentialRevenue": 46423.49,
    "riskExposure": 0.52,
    "generatedAt": "2024-02-13T13:00:00Z",
    "status": "In Progress",
    "assignedTo": "Sarah Johnson",
    "relatedAlerts": []
  },
  {
    "id": 39,
    "customerId": 3932,
    "customerName": "Customer 3932",
    "insightType": "Cross-Sell Opportunity",
    "category": "Customer Retention",
    "description": "Automated CRM insight generated based on recent customer behavior and transaction patterns.",
    "priority": 2,
    "recommendedAction": "Schedule personalized financial advisory session",
    "potentialRevenue": 11141.26,
    "riskExposure": 0.76,
    "generatedAt": "2024-02-09T04:00:00Z",
    "status": "In Progress",
    "assignedTo": "Daniel Lee",
    "relatedAlerts": []
  },
  {
    "id": 40,
    "customerId": 4084,
    "customerName": "Customer 4084",
    "insightType": "Up-Sell Opportunity",
    "category": "Risk Mitigation",
    "description": "Automated CRM insight generated based on recent customer behavior and transaction patterns.",
    "priority": 5,
    "recommendedAction": "Schedule personalized financial advisory session",
    "potentialRevenue": 10068.96,
    "riskExposure": 0.5,
    "generatedAt": "2024-02-03T21:00:00Z",
    "status": "In Progress",
    "assignedTo": "Michael Brown",
    "relatedAlerts": []
  },
  {
    "id": 41,
    "customerId": 1867,
    "customerName": "Customer 1867",
    "insightType": "Up-Sell Opportunity",
    "category": "Customer Experience",
    "description": "Automated CRM insight generated based on recent customer behavior and transaction patterns.",
    "priority": 1,
    "recommendedAction": "Offer premium investment portfolio management services",
    "potentialRevenue": 38576.48,
    "riskExposure": 0.82,
    "generatedAt": "2024-02-21T14:00:00Z",
    "status": "Closed",
    "assignedTo": "Priya Patel",
    "relatedAlerts": []
  },
  {
    "id": 42,
    "customerId": 3212,
    "customerName": "Customer 3212",
    "insightType": "Cross-Sell Opportunity",
    "category": "Risk Mitigation",
    "description": "Automated CRM insight generated based on recent customer behavior and transaction patterns.",
    "priority": 3,
    "recommendedAction": "Introduce bundled banking products",
    "potentialRevenue": 11049.34,
    "riskExposure": 0.73,
    "generatedAt": "2024-02-05T04:00:00Z",
    "status": "In Progress",
    "assignedTo": "Priya Patel",
    "relatedAlerts": []
  },
  {
    "id": 43,
    "customerId": 3830,
    "customerName": "Customer 3830",
    "insightType": "Churn Prevention",
    "category": "Risk Mitigation",
    "description": "Automated CRM insight generated based on recent customer behavior and transaction patterns.",
    "priority": 2,
    "recommendedAction": "Schedule personalized financial advisory session",
    "potentialRevenue": 17831.97,
    "riskExposure": 0.37,
    "generatedAt": "2024-02-03T04:00:00Z",
    "status": "Open",
    "assignedTo": "Priya Patel",
    "relatedAlerts": []
  },
  {
    "id": 44,
    "customerId": 8856,
    "customerName": "Customer 8856",
    "insightType": "Up-Sell Opportunity",
    "category": "Customer Retention",
    "description": "Automated CRM insight generated based on recent customer behavior and transaction patterns.",
    "priority": 5,
    "recommendedAction": "Offer premium investment portfolio management services",
    "potentialRevenue": 5409.75,
    "riskExposure": 0.74,
    "generatedAt": "2024-02-02T12:00:00Z",
    "status": "In Progress",
    "assignedTo": "Priya Patel",
    "relatedAlerts": []
  },
  {
    "id": 45,
    "customerId": 5248,
    "customerName": "Customer 5248",
    "insightType": "Up-Sell Opportunity",
    "category": "Revenue Growth",
    "description": "Automated CRM insight generated based on recent customer behavior and transaction patterns.",
    "priority": 4,
    "recommendedAction": "Schedule personalized financial advisory session",
    "potentialRevenue": 34677.46,
    "riskExposure": 0.9,
    "generatedAt": "2024-02-06T03:00:00Z",
    "status": "Open",
    "assignedTo": "Daniel Lee",
    "relatedAlerts": []
  },
  {
    "id": 46,
    "customerId": 5555,
    "customerName": "Customer 5555",
    "insightType": "Customer Engagement",
    "category": "Risk Mitigation",
    "description": "Automated CRM insight generated based on recent customer behavior and transaction patterns.",
    "priority": 3,
    "recommendedAction": "Offer digital banking feature walkthrough",
    "potentialRevenue": 35017.77,
    "riskExposure": 0.72,
    "generatedAt": "2024-02-08T23:00:00Z",
    "status": "Open",
    "assignedTo": "Sarah Johnson",
    "relatedAlerts": []
  },
  {
    "id": 47,
    "customerId": 5220,
    "customerName": "Customer 5220",
    "insightType": "Churn Prevention",
    "category": "Customer Retention",
    "description": "Automated CRM insight generated based on recent customer behavior and transaction patterns.",
    "priority": 1,
    "recommendedAction": "Provide loyalty benefits to improve retention",
    "potentialRevenue": 32915.48,
    "riskExposure": 0.26,
    "generatedAt": "2024-02-02T04:00:00Z",
    "status": "In Progress",
    "assignedTo": "Sarah Johnson",
    "relatedAlerts": []
  },
  {
    "id": 48,
    "customerId": 6918,
    "customerName": "Customer 6918",
    "insightType": "Customer Engagement",
    "category": "Customer Experience",
    "description": "Automated CRM insight generated based on recent customer behavior and transaction patterns.",
    "priority": 1,
    "recommendedAction": "Provide loyalty benefits to improve retention",
    "potentialRevenue": 14775.29,
    "riskExposure": 0.69,
    "generatedAt": "2024-02-11T05:00:00Z",
    "status": "Open",
    "assignedTo": "Sarah Johnson",
    "relatedAlerts": []
  },
  {
    "id": 49,
    "customerId": 2990,
    "customerName": "Customer 2990",
    "insightType": "Churn Prevention",
    "category": "Revenue Growth",
    "description": "Automated CRM insight generated based on recent customer behavior and transaction patterns.",
    "priority": 2,
    "recommendedAction": "Schedule personalized financial advisory session",
    "potentialRevenue": 5651.06,
    "riskExposure": 0.42,
    "generatedAt": "2024-02-23T08:00:00Z",
    "status": "Open",
    "assignedTo": "Sarah Johnson",
    "relatedAlerts": []
  },
  {
    "id": 50,
    "customerId": 2439,
    "customerName": "Customer 2439",
    "insightType": "Product Recommendation",
    "category": "Risk Mitigation",
    "description": "Automated CRM insight generated based on recent customer behavior and transaction patterns.",
    "priority": 5,
    "recommendedAction": "Offer premium investment portfolio management services",
    "potentialRevenue": 38877.38,
    "riskExposure": 0.4,
    "generatedAt": "2024-02-06T19:00:00Z",
    "status": "Open",
    "assignedTo": "Michael Brown",
    "relatedAlerts": []
  },
  {
    "id": 51,
    "customerId": 2673,
    "customerName": "Customer 2673",
    "insightType": "Retention Risk",
    "category": "Risk Mitigation",
    "description": "Automated CRM insight generated based on recent customer behavior and transaction patterns.",
    "priority": 1,
    "recommendedAction": "Provide loyalty benefits to improve retention",
    "potentialRevenue": 36639.75,
    "riskExposure": 0.69,
    "generatedAt": "2024-02-04T00:00:00Z",
    "status": "Open",
    "assignedTo": "Amit Sharma",
    "relatedAlerts": []
  },
  {
    "id": 52,
    "customerId": 9338,
    "customerName": "Customer 9338",
    "insightType": "Product Recommendation",
    "category": "Risk Mitigation",
    "description": "Automated CRM insight generated based on recent customer behavior and transaction patterns.",
    "priority": 5,
    "recommendedAction": "Recommend credit card upgrade with higher limits",
    "potentialRevenue": 32351.44,
    "riskExposure": 0.38,
    "generatedAt": "2024-02-01T03:00:00Z",
    "status": "Open",
    "assignedTo": "Michael Brown",
    "relatedAlerts": []
  },
  {
    "id": 53,
    "customerId": 6578,
    "customerName": "Customer 6578",
    "insightType": "Cross-Sell Opportunity",
    "category": "Customer Experience",
    "description": "Automated CRM insight generated based on recent customer behavior and transaction patterns.",
    "priority": 2,
    "recommendedAction": "Introduce bundled banking products",
    "potentialRevenue": 39271.71,
    "riskExposure": 0.18,
    "generatedAt": "2024-02-14T06:00:00Z",
    "status": "Closed",
    "assignedTo": "Amit Sharma",
    "relatedAlerts": []
  },
  {
    "id": 54,
    "customerId": 8128,
    "customerName": "Customer 8128",
    "insightType": "Retention Risk",
    "category": "Risk Mitigation",
    "description": "Automated CRM insight generated based on recent customer behavior and transaction patterns.",
    "priority": 4,
    "recommendedAction": "Offer digital banking feature walkthrough",
    "potentialRevenue": 30893.89,
    "riskExposure": 0.87,
    "generatedAt": "2024-02-12T23:00:00Z",
    "status": "Closed",
    "assignedTo": "Michael Brown",
    "relatedAlerts": []
  },
  {
    "id": 55,
    "customerId": 5378,
    "customerName": "Customer 5378",
    "insightType": "Churn Prevention",
    "category": "Risk Mitigation",
    "description": "Automated CRM insight generated based on recent customer behavior and transaction patterns.",
    "priority": 3,
    "recommendedAction": "Offer premium investment portfolio management services",
    "potentialRevenue": 9528.44,
    "riskExposure": 0.59,
    "generatedAt": "2024-02-09T05:00:00Z",
    "status": "Closed",
    "assignedTo": "Emily Clark",
    "relatedAlerts": []
  },
  {
    "id": 56,
    "customerId": 4265,
    "customerName": "Customer 4265",
    "insightType": "Customer Engagement",
    "category": "Revenue Growth",
    "description": "Automated CRM insight generated based on recent customer behavior and transaction patterns.",
    "priority": 3,
    "recommendedAction": "Offer premium investment portfolio management services",
    "potentialRevenue": 32947.66,
    "riskExposure": 0.89,
    "generatedAt": "2024-02-15T10:00:00Z",
    "status": "In Progress",
    "assignedTo": "Emily Clark",
    "relatedAlerts": []
  },
  {
    "id": 57,
    "customerId": 9322,
    "customerName": "Customer 9322",
    "insightType": "Retention Risk",
    "category": "Risk Mitigation",
    "description": "Automated CRM insight generated based on recent customer behavior and transaction patterns.",
    "priority": 1,
    "recommendedAction": "Provide loyalty benefits to improve retention",
    "potentialRevenue": 23054.04,
    "riskExposure": 0.33,
    "generatedAt": "2024-02-20T13:00:00Z",
    "status": "Closed",
    "assignedTo": "Emily Clark",
    "relatedAlerts": []
  },
  {
    "id": 58,
    "customerId": 6434,
    "customerName": "Customer 6434",
    "insightType": "Churn Prevention",
    "category": "Revenue Growth",
    "description": "Automated CRM insight generated based on recent customer behavior and transaction patterns.",
    "priority": 2,
    "recommendedAction": "Provide loyalty benefits to improve retention",
    "potentialRevenue": 26991.09,
    "riskExposure": 0.03,
    "generatedAt": "2024-02-26T16:00:00Z",
    "status": "In Progress",
    "assignedTo": "Priya Patel",
    "relatedAlerts": []
  },
  {
    "id": 59,
    "customerId": 4904,
    "customerName": "Customer 4904",
    "insightType": "Churn Prevention",
    "category": "Risk Mitigation",
    "description": "Automated CRM insight generated based on recent customer behavior and transaction patterns.",
    "priority": 5,
    "recommendedAction": "Provide loyalty benefits to improve retention",
    "potentialRevenue": 37244.21,
    "riskExposure": 0.18,
    "generatedAt": "2024-02-19T19:00:00Z",
    "status": "Closed",
    "assignedTo": "Amit Sharma",
    "relatedAlerts": []
  },
  {
    "id": 60,
    "customerId": 7065,
    "customerName": "Customer 7065",
    "insightType": "Product Recommendation",
    "category": "Risk Mitigation",
    "description": "Automated CRM insight generated based on recent customer behavior and transaction patterns.",
    "priority": 5,
    "recommendedAction": "Offer digital banking feature walkthrough",
    "potentialRevenue": 3827.19,
    "riskExposure": 0.54,
    "generatedAt": "2024-02-21T05:00:00Z",
    "status": "In Progress",
    "assignedTo": "Daniel Lee",
    "relatedAlerts": []
  },
  {
    "id": 61,
    "customerId": 9404,
    "customerName": "Customer 9404",
    "insightType": "Up-Sell Opportunity",
    "category": "Customer Retention",
    "description": "Automated CRM insight generated based on recent customer behavior and transaction patterns.",
    "priority": 3,
    "recommendedAction": "Provide loyalty benefits to improve retention",
    "potentialRevenue": 35012.86,
    "riskExposure": 0.59,
    "generatedAt": "2024-02-06T15:00:00Z",
    "status": "Closed",
    "assignedTo": "Emily Clark",
    "relatedAlerts": []
  },
  {
    "id": 62,
    "customerId": 2753,
    "customerName": "Customer 2753",
    "insightType": "Customer Engagement",
    "category": "Customer Retention",
    "description": "Automated CRM insight generated based on recent customer behavior and transaction patterns.",
    "priority": 1,
    "recommendedAction": "Offer premium investment portfolio management services",
    "potentialRevenue": 28709.05,
    "riskExposure": 0.09,
    "generatedAt": "2024-02-19T08:00:00Z",
    "status": "Open",
    "assignedTo": "Emily Clark",
    "relatedAlerts": []
  },
  {
    "id": 63,
    "customerId": 4316,
    "customerName": "Customer 4316",
    "insightType": "Retention Risk",
    "category": "Customer Retention",
    "description": "Automated CRM insight generated based on recent customer behavior and transaction patterns.",
    "priority": 1,
    "recommendedAction": "Recommend credit card upgrade with higher limits",
    "potentialRevenue": 29139.13,
    "riskExposure": 0.21,
    "generatedAt": "2024-02-04T12:00:00Z",
    "status": "In Progress",
    "assignedTo": "Amit Sharma",
    "relatedAlerts": []
  },
  {
    "id": 64,
    "customerId": 4464,
    "customerName": "Customer 4464",
    "insightType": "Customer Engagement",
    "category": "Risk Mitigation",
    "description": "Automated CRM insight generated based on recent customer behavior and transaction patterns.",
    "priority": 1,
    "recommendedAction": "Schedule personalized financial advisory session",
    "potentialRevenue": 38676.6,
    "riskExposure": 0.38,
    "generatedAt": "2024-02-12T19:00:00Z",
    "status": "In Progress",
    "assignedTo": "Sarah Johnson",
    "relatedAlerts": []
  },
  {
    "id": 65,
    "customerId": 8945,
    "customerName": "Customer 8945",
    "insightType": "Product Recommendation",
    "category": "Risk Mitigation",
    "description": "Automated CRM insight generated based on recent customer behavior and transaction patterns.",
    "priority": 3,
    "recommendedAction": "Schedule personalized financial advisory session",
    "potentialRevenue": 7393.04,
    "riskExposure": 0.2,
    "generatedAt": "2024-02-16T21:00:00Z",
    "status": "Open",
    "assignedTo": "Priya Patel",
    "relatedAlerts": []
  },
  {
    "id": 66,
    "customerId": 3280,
    "customerName": "Customer 3280",
    "insightType": "Cross-Sell Opportunity",
    "category": "Customer Retention",
    "description": "Automated CRM insight generated based on recent customer behavior and transaction patterns.",
    "priority": 3,
    "recommendedAction": "Introduce bundled banking products",
    "potentialRevenue": 8091.3,
    "riskExposure": 0.13,
    "generatedAt": "2024-02-16T00:00:00Z",
    "status": "Open",
    "assignedTo": "Michael Brown",
    "relatedAlerts": []
  },
  {
    "id": 67,
    "customerId": 4542,
    "customerName": "Customer 4542",
    "insightType": "Churn Prevention",
    "category": "Customer Experience",
    "description": "Automated CRM insight generated based on recent customer behavior and transaction patterns.",
    "priority": 3,
    "recommendedAction": "Recommend credit card upgrade with higher limits",
    "potentialRevenue": 30244.44,
    "riskExposure": 0.04,
    "generatedAt": "2024-02-25T12:00:00Z",
    "status": "Open",
    "assignedTo": "Amit Sharma",
    "relatedAlerts": []
  },
  {
    "id": 68,
    "customerId": 4461,
    "customerName": "Customer 4461",
    "insightType": "Customer Engagement",
    "category": "Customer Retention",
    "description": "Automated CRM insight generated based on recent customer behavior and transaction patterns.",
    "priority": 1,
    "recommendedAction": "Offer premium investment portfolio management services",
    "potentialRevenue": 19378.88,
    "riskExposure": 0.69,
    "generatedAt": "2024-02-02T03:00:00Z",
    "status": "Open",
    "assignedTo": "Daniel Lee",
    "relatedAlerts": []
  },
  {
    "id": 69,
    "customerId": 4106,
    "customerName": "Customer 4106",
    "insightType": "Cross-Sell Opportunity",
    "category": "Risk Mitigation",
    "description": "Automated CRM insight generated based on recent customer behavior and transaction patterns.",
    "priority": 2,
    "recommendedAction": "Offer premium investment portfolio management services",
    "potentialRevenue": 18390.29,
    "riskExposure": 0.79,
    "generatedAt": "2024-02-24T15:00:00Z",
    "status": "In Progress",
    "assignedTo": "Amit Sharma",
    "relatedAlerts": []
  },
  {
    "id": 70,
    "customerId": 6377,
    "customerName": "Customer 6377",
    "insightType": "Customer Engagement",
    "category": "Customer Experience",
    "description": "Automated CRM insight generated based on recent customer behavior and transaction patterns.",
    "priority": 3,
    "recommendedAction": "Schedule personalized financial advisory session",
    "potentialRevenue": 49340.17,
    "riskExposure": 0.58,
    "generatedAt": "2024-02-23T20:00:00Z",
    "status": "Open",
    "assignedTo": "Sarah Johnson",
    "relatedAlerts": []
  },
  {
    "id": 71,
    "customerId": 4063,
    "customerName": "Customer 4063",
    "insightType": "Product Recommendation",
    "category": "Customer Experience",
    "description": "Automated CRM insight generated based on recent customer behavior and transaction patterns.",
    "priority": 3,
    "recommendedAction": "Offer premium investment portfolio management services",
    "potentialRevenue": 32533.32,
    "riskExposure": 0.6,
    "generatedAt": "2024-02-01T11:00:00Z",
    "status": "In Progress",
    "assignedTo": "Emily Clark",
    "relatedAlerts": []
  },
  {
    "id": 72,
    "customerId": 1303,
    "customerName": "Customer 1303",
    "insightType": "Product Recommendation",
    "category": "Revenue Growth",
    "description": "Automated CRM insight generated based on recent customer behavior and transaction patterns.",
    "priority": 1,
    "recommendedAction": "Provide loyalty benefits to improve retention",
    "potentialRevenue": 10729.43,
    "riskExposure": 0.35,
    "generatedAt": "2024-02-10T15:00:00Z",
    "status": "Closed",
    "assignedTo": "Emily Clark",
    "relatedAlerts": []
  },
  {
    "id": 73,
    "customerId": 5548,
    "customerName": "Customer 5548",
    "insightType": "Customer Engagement",
    "category": "Customer Retention",
    "description": "Automated CRM insight generated based on recent customer behavior and transaction patterns.",
    "priority": 2,
    "recommendedAction": "Schedule personalized financial advisory session",
    "potentialRevenue": 34336.9,
    "riskExposure": 0.44,
    "generatedAt": "2024-02-09T16:00:00Z",
    "status": "In Progress",
    "assignedTo": "Priya Patel",
    "relatedAlerts": []
  },
  {
    "id": 74,
    "customerId": 5222,
    "customerName": "Customer 5222",
    "insightType": "Up-Sell Opportunity",
    "category": "Customer Experience",
    "description": "Automated CRM insight generated based on recent customer behavior and transaction patterns.",
    "priority": 4,
    "recommendedAction": "Recommend credit card upgrade with higher limits",
    "potentialRevenue": 13452.27,
    "riskExposure": 0.43,
    "generatedAt": "2024-02-17T13:00:00Z",
    "status": "Open",
    "assignedTo": "Daniel Lee",
    "relatedAlerts": []
  },
  {
    "id": 75,
    "customerId": 3108,
    "customerName": "Customer 3108",
    "insightType": "Product Recommendation",
    "category": "Revenue Growth",
    "description": "Automated CRM insight generated based on recent customer behavior and transaction patterns.",
    "priority": 3,
    "recommendedAction": "Provide loyalty benefits to improve retention",
    "potentialRevenue": 38564.55,
    "riskExposure": 0.36,
    "generatedAt": "2024-02-27T17:00:00Z",
    "status": "Closed",
    "assignedTo": "Daniel Lee",
    "relatedAlerts": []
  },
  {
    "id": 76,
    "customerId": 8753,
    "customerName": "Customer 8753",
    "insightType": "Churn Prevention",
    "category": "Customer Experience",
    "description": "Automated CRM insight generated based on recent customer behavior and transaction patterns.",
    "priority": 3,
    "recommendedAction": "Provide loyalty benefits to improve retention",
    "potentialRevenue": 36136.34,
    "riskExposure": 0.31,
    "generatedAt": "2024-02-18T03:00:00Z",
    "status": "Closed",
    "assignedTo": "Daniel Lee",
    "relatedAlerts": []
  },
  {
    "id": 77,
    "customerId": 8671,
    "customerName": "Customer 8671",
    "insightType": "Churn Prevention",
    "category": "Customer Experience",
    "description": "Automated CRM insight generated based on recent customer behavior and transaction patterns.",
    "priority": 4,
    "recommendedAction": "Offer premium investment portfolio management services",
    "potentialRevenue": 13330.69,
    "riskExposure": 0.42,
    "generatedAt": "2024-02-15T02:00:00Z",
    "status": "Open",
    "assignedTo": "Sarah Johnson",
    "relatedAlerts": []
  },
  {
    "id": 78,
    "customerId": 5221,
    "customerName": "Customer 5221",
    "insightType": "Cross-Sell Opportunity",
    "category": "Customer Retention",
    "description": "Automated CRM insight generated based on recent customer behavior and transaction patterns.",
    "priority": 3,
    "recommendedAction": "Offer digital banking feature walkthrough",
    "potentialRevenue": 38576.85,
    "riskExposure": 0.43,
    "generatedAt": "2024-02-15T05:00:00Z",
    "status": "In Progress",
    "assignedTo": "Michael Brown",
    "relatedAlerts": []
  },
  {
    "id": 79,
    "customerId": 8179,
    "customerName": "Customer 8179",
    "insightType": "Product Recommendation",
    "category": "Risk Mitigation",
    "description": "Automated CRM insight generated based on recent customer behavior and transaction patterns.",
    "priority": 2,
    "recommendedAction": "Recommend credit card upgrade with higher limits",
    "potentialRevenue": 30223.19,
    "riskExposure": 0.89,
    "generatedAt": "2024-02-16T11:00:00Z",
    "status": "Closed",
    "assignedTo": "Amit Sharma",
    "relatedAlerts": []
  },
  {
    "id": 80,
    "customerId": 9176,
    "customerName": "Customer 9176",
    "insightType": "Up-Sell Opportunity",
    "category": "Customer Experience",
    "description": "Automated CRM insight generated based on recent customer behavior and transaction patterns.",
    "priority": 4,
    "recommendedAction": "Introduce bundled banking products",
    "potentialRevenue": 39686.76,
    "riskExposure": 0.74,
    "generatedAt": "2024-02-06T15:00:00Z",
    "status": "Open",
    "assignedTo": "Priya Patel",
    "relatedAlerts": []
  },
  {
    "id": 81,
    "customerId": 7786,
    "customerName": "Customer 7786",
    "insightType": "Retention Risk",
    "category": "Risk Mitigation",
    "description": "Automated CRM insight generated based on recent customer behavior and transaction patterns.",
    "priority": 4,
    "recommendedAction": "Schedule personalized financial advisory session",
    "potentialRevenue": 29298.91,
    "riskExposure": 0.13,
    "generatedAt": "2024-02-15T08:00:00Z",
    "status": "Open",
    "assignedTo": "Priya Patel",
    "relatedAlerts": []
  },
  {
    "id": 82,
    "customerId": 5712,
    "customerName": "Customer 5712",
    "insightType": "Cross-Sell Opportunity",
    "category": "Customer Experience",
    "description": "Automated CRM insight generated based on recent customer behavior and transaction patterns.",
    "priority": 4,
    "recommendedAction": "Offer digital banking feature walkthrough",
    "potentialRevenue": 21046.83,
    "riskExposure": 0.0,
    "generatedAt": "2024-02-17T09:00:00Z",
    "status": "In Progress",
    "assignedTo": "Sarah Johnson",
    "relatedAlerts": []
  },
  {
    "id": 83,
    "customerId": 4291,
    "customerName": "Customer 4291",
    "insightType": "Product Recommendation",
    "category": "Risk Mitigation",
    "description": "Automated CRM insight generated based on recent customer behavior and transaction patterns.",
    "priority": 3,
    "recommendedAction": "Recommend credit card upgrade with higher limits",
    "potentialRevenue": 49513.95,
    "riskExposure": 0.11,
    "generatedAt": "2024-02-04T08:00:00Z",
    "status": "In Progress",
    "assignedTo": "Michael Brown",
    "relatedAlerts": []
  },
  {
    "id": 84,
    "customerId": 5763,
    "customerName": "Customer 5763",
    "insightType": "Customer Engagement",
    "category": "Customer Experience",
    "description": "Automated CRM insight generated based on recent customer behavior and transaction patterns.",
    "priority": 3,
    "recommendedAction": "Recommend credit card upgrade with higher limits",
    "potentialRevenue": 47877.69,
    "riskExposure": 0.73,
    "generatedAt": "2024-02-15T19:00:00Z",
    "status": "Open",
    "assignedTo": "Daniel Lee",
    "relatedAlerts": []
  },
  {
    "id": 85,
    "customerId": 2183,
    "customerName": "Customer 2183",
    "insightType": "Customer Engagement",
    "category": "Risk Mitigation",
    "description": "Automated CRM insight generated based on recent customer behavior and transaction patterns.",
    "priority": 4,
    "recommendedAction": "Offer premium investment portfolio management services",
    "potentialRevenue": 33187.3,
    "riskExposure": 0.9,
    "generatedAt": "2024-02-27T21:00:00Z",
    "status": "Open",
    "assignedTo": "Emily Clark",
    "relatedAlerts": []
  },
  {
    "id": 86,
    "customerId": 2793,
    "customerName": "Customer 2793",
    "insightType": "Up-Sell Opportunity",
    "category": "Risk Mitigation",
    "description": "Automated CRM insight generated based on recent customer behavior and transaction patterns.",
    "priority": 3,
    "recommendedAction": "Offer premium investment portfolio management services",
    "potentialRevenue": 49494.24,
    "riskExposure": 0.01,
    "generatedAt": "2024-02-20T23:00:00Z",
    "status": "Closed",
    "assignedTo": "Priya Patel",
    "relatedAlerts": []
  },
  {
    "id": 87,
    "customerId": 5512,
    "customerName": "Customer 5512",
    "insightType": "Churn Prevention",
    "category": "Customer Retention",
    "description": "Automated CRM insight generated based on recent customer behavior and transaction patterns.",
    "priority": 1,
    "recommendedAction": "Provide loyalty benefits to improve retention",
    "potentialRevenue": 47641.42,
    "riskExposure": 0.28,
    "generatedAt": "2024-02-25T19:00:00Z",
    "status": "Closed",
    "assignedTo": "Emily Clark",
    "relatedAlerts": []
  },
  {
    "id": 88,
    "customerId": 5574,
    "customerName": "Customer 5574",
    "insightType": "Churn Prevention",
    "category": "Customer Experience",
    "description": "Automated CRM insight generated based on recent customer behavior and transaction patterns.",
    "priority": 3,
    "recommendedAction": "Provide loyalty benefits to improve retention",
    "potentialRevenue": 25678.53,
    "riskExposure": 0.79,
    "generatedAt": "2024-02-07T17:00:00Z",
    "status": "Closed",
    "assignedTo": "Daniel Lee",
    "relatedAlerts": []
  },
  {
    "id": 89,
    "customerId": 7485,
    "customerName": "Customer 7485",
    "insightType": "Churn Prevention",
    "category": "Revenue Growth",
    "description": "Automated CRM insight generated based on recent customer behavior and transaction patterns.",
    "priority": 1,
    "recommendedAction": "Schedule personalized financial advisory session",
    "potentialRevenue": 44585.64,
    "riskExposure": 0.39,
    "generatedAt": "2024-02-23T08:00:00Z",
    "status": "Open",
    "assignedTo": "Amit Sharma",
    "relatedAlerts": []
  },
  {
    "id": 90,
    "customerId": 1817,
    "customerName": "Customer 1817",
    "insightType": "Up-Sell Opportunity",
    "category": "Customer Retention",
    "description": "Automated CRM insight generated based on recent customer behavior and transaction patterns.",
    "priority": 4,
    "recommendedAction": "Offer premium investment portfolio management services",
    "potentialRevenue": 18074.65,
    "riskExposure": 0.05,
    "generatedAt": "2024-02-21T14:00:00Z",
    "status": "Open",
    "assignedTo": "Priya Patel",
    "relatedAlerts": []
  },
  {
    "id": 91,
    "customerId": 4326,
    "customerName": "Customer 4326",
    "insightType": "Retention Risk",
    "category": "Revenue Growth",
    "description": "Automated CRM insight generated based on recent customer behavior and transaction patterns.",
    "priority": 3,
    "recommendedAction": "Schedule personalized financial advisory session",
    "potentialRevenue": 19375.63,
    "riskExposure": 0.77,
    "generatedAt": "2024-02-16T05:00:00Z",
    "status": "Open",
    "assignedTo": "Michael Brown",
    "relatedAlerts": []
  },
  {
    "id": 92,
    "customerId": 5023,
    "customerName": "Customer 5023",
    "insightType": "Retention Risk",
    "category": "Revenue Growth",
    "description": "Automated CRM insight generated based on recent customer behavior and transaction patterns.",
    "priority": 5,
    "recommendedAction": "Offer digital banking feature walkthrough",
    "potentialRevenue": 44417.01,
    "riskExposure": 0.76,
    "generatedAt": "2024-02-09T06:00:00Z",
    "status": "Open",
    "assignedTo": "Sarah Johnson",
    "relatedAlerts": []
  },
  {
    "id": 93,
    "customerId": 9461,
    "customerName": "Customer 9461",
    "insightType": "Churn Prevention",
    "category": "Customer Experience",
    "description": "Automated CRM insight generated based on recent customer behavior and transaction patterns.",
    "priority": 5,
    "recommendedAction": "Recommend credit card upgrade with higher limits",
    "potentialRevenue": 10600.18,
    "riskExposure": 0.21,
    "generatedAt": "2024-02-09T21:00:00Z",
    "status": "In Progress",
    "assignedTo": "Sarah Johnson",
    "relatedAlerts": []
  },
  {
    "id": 94,
    "customerId": 9364,
    "customerName": "Customer 9364",
    "insightType": "Product Recommendation",
    "category": "Customer Experience",
    "description": "Automated CRM insight generated based on recent customer behavior and transaction patterns.",
    "priority": 3,
    "recommendedAction": "Offer digital banking feature walkthrough",
    "potentialRevenue": 5879.53,
    "riskExposure": 0.67,
    "generatedAt": "2024-02-14T09:00:00Z",
    "status": "Open",
    "assignedTo": "Amit Sharma",
    "relatedAlerts": []
  },
  {
    "id": 95,
    "customerId": 1442,
    "customerName": "Customer 1442",
    "insightType": "Churn Prevention",
    "category": "Customer Retention",
    "description": "Automated CRM insight generated based on recent customer behavior and transaction patterns.",
    "priority": 1,
    "recommendedAction": "Provide loyalty benefits to improve retention",
    "potentialRevenue": 41834.89,
    "riskExposure": 0.62,
    "generatedAt": "2024-02-08T19:00:00Z",
    "status": "Closed",
    "assignedTo": "Amit Sharma",
    "relatedAlerts": []
  },
  {
    "id": 96,
    "customerId": 8871,
    "customerName": "Customer 8871",
    "insightType": "Up-Sell Opportunity",
    "category": "Revenue Growth",
    "description": "Automated CRM insight generated based on recent customer behavior and transaction patterns.",
    "priority": 5,
    "recommendedAction": "Schedule personalized financial advisory session",
    "potentialRevenue": 13469.2,
    "riskExposure": 0.39,
    "generatedAt": "2024-02-17T18:00:00Z",
    "status": "Open",
    "assignedTo": "Amit Sharma",
    "relatedAlerts": []
  },
  {
    "id": 97,
    "customerId": 4060,
    "customerName": "Customer 4060",
    "insightType": "Churn Prevention",
    "category": "Customer Experience",
    "description": "Automated CRM insight generated based on recent customer behavior and transaction patterns.",
    "priority": 1,
    "recommendedAction": "Recommend credit card upgrade with higher limits",
    "potentialRevenue": 6151.69,
    "riskExposure": 0.31,
    "generatedAt": "2024-02-15T11:00:00Z",
    "status": "In Progress",
    "assignedTo": "Priya Patel",
    "relatedAlerts": []
  },
  {
    "id": 98,
    "customerId": 3938,
    "customerName": "Customer 3938",
    "insightType": "Churn Prevention",
    "category": "Customer Experience",
    "description": "Automated CRM insight generated based on recent customer behavior and transaction patterns.",
    "priority": 1,
    "recommendedAction": "Provide loyalty benefits to improve retention",
    "potentialRevenue": 36095.47,
    "riskExposure": 0.78,
    "generatedAt": "2024-02-27T19:00:00Z",
    "status": "In Progress",
    "assignedTo": "Emily Clark",
    "relatedAlerts": []
  },
  {
    "id": 99,
    "customerId": 6419,
    "customerName": "Customer 6419",
    "insightType": "Customer Engagement",
    "category": "Revenue Growth",
    "description": "Automated CRM insight generated based on recent customer behavior and transaction patterns.",
    "priority": 4,
    "recommendedAction": "Introduce bundled banking products",
    "potentialRevenue": 26879.33,
    "riskExposure": 0.07,
    "generatedAt": "2024-02-19T18:00:00Z",
    "status": "In Progress",
    "assignedTo": "Daniel Lee",
    "relatedAlerts": []
  },
  {
    "id": 100,
    "customerId": 5174,
    "customerName": "Customer 5174",
    "insightType": "Customer Engagement",
    "category": "Customer Retention",
    "description": "Automated CRM insight generated based on recent customer behavior and transaction patterns.",
    "priority": 1,
    "recommendedAction": "Provide loyalty benefits to improve retention",
    "potentialRevenue": 40872.33,
    "riskExposure": 0.03,
    "generatedAt": "2024-02-23T00:00:00Z",
    "status": "Closed",
    "assignedTo": "Michael Brown",
    "relatedAlerts": []
  },
  {
    "id": 101,
    "customerId": 3020,
    "customerName": "Customer 3020",
    "insightType": "Churn Prevention",
    "category": "Customer Experience",
    "description": "Automated CRM insight generated based on recent customer behavior and transaction patterns.",
    "priority": 4,
    "recommendedAction": "Recommend credit card upgrade with higher limits",
    "potentialRevenue": 42155.43,
    "riskExposure": 0.73,
    "generatedAt": "2024-02-10T06:00:00Z",
    "status": "Closed",
    "assignedTo": "Amit Sharma",
    "relatedAlerts": []
  },
  {
    "id": 102,
    "customerId": 8959,
    "customerName": "Customer 8959",
    "insightType": "Churn Prevention",
    "category": "Revenue Growth",
    "description": "Automated CRM insight generated based on recent customer behavior and transaction patterns.",
    "priority": 5,
    "recommendedAction": "Offer premium investment portfolio management services",
    "potentialRevenue": 29602.45,
    "riskExposure": 0.53,
    "generatedAt": "2024-02-06T07:00:00Z",
    "status": "In Progress",
    "assignedTo": "Michael Brown",
    "relatedAlerts": []
  },
  {
    "id": 103,
    "customerId": 2234,
    "customerName": "Customer 2234",
    "insightType": "Retention Risk",
    "category": "Risk Mitigation",
    "description": "Automated CRM insight generated based on recent customer behavior and transaction patterns.",
    "priority": 5,
    "recommendedAction": "Schedule personalized financial advisory session",
    "potentialRevenue": 26449.56,
    "riskExposure": 0.12,
    "generatedAt": "2024-02-27T11:00:00Z",
    "status": "Closed",
    "assignedTo": "Emily Clark",
    "relatedAlerts": []
  },
  {
    "id": 104,
    "customerId": 5688,
    "customerName": "Customer 5688",
    "insightType": "Customer Engagement",
    "category": "Revenue Growth",
    "description": "Automated CRM insight generated based on recent customer behavior and transaction patterns.",
    "priority": 4,
    "recommendedAction": "Offer premium investment portfolio management services",
    "potentialRevenue": 22112.13,
    "riskExposure": 0.9,
    "generatedAt": "2024-02-10T03:00:00Z",
    "status": "In Progress",
    "assignedTo": "Sarah Johnson",
    "relatedAlerts": []
  },
  {
    "id": 105,
    "customerId": 1078,
    "customerName": "Customer 1078",
    "insightType": "Up-Sell Opportunity",
    "category": "Customer Experience",
    "description": "Automated CRM insight generated based on recent customer behavior and transaction patterns.",
    "priority": 4,
    "recommendedAction": "Introduce bundled banking products",
    "potentialRevenue": 8875.35,
    "riskExposure": 0.52,
    "generatedAt": "2024-02-07T06:00:00Z",
    "status": "Open",
    "assignedTo": "Michael Brown",
    "relatedAlerts": []
  },
  {
    "id": 106,
    "customerId": 6854,
    "customerName": "Customer 6854",
    "insightType": "Churn Prevention",
    "category": "Customer Retention",
    "description": "Automated CRM insight generated based on recent customer behavior and transaction patterns.",
    "priority": 4,
    "recommendedAction": "Recommend credit card upgrade with higher limits",
    "potentialRevenue": 8288.16,
    "riskExposure": 0.23,
    "generatedAt": "2024-02-14T03:00:00Z",
    "status": "Closed",
    "assignedTo": "Daniel Lee",
    "relatedAlerts": []
  },
  {
    "id": 107,
    "customerId": 3355,
    "customerName": "Customer 3355",
    "insightType": "Up-Sell Opportunity",
    "category": "Risk Mitigation",
    "description": "Automated CRM insight generated based on recent customer behavior and transaction patterns.",
    "priority": 1,
    "recommendedAction": "Offer digital banking feature walkthrough",
    "potentialRevenue": 41550.61,
    "riskExposure": 0.83,
    "generatedAt": "2024-02-02T04:00:00Z",
    "status": "Open",
    "assignedTo": "Amit Sharma",
    "relatedAlerts": []
  },
  {
    "id": 108,
    "customerId": 5120,
    "customerName": "Customer 5120",
    "insightType": "Product Recommendation",
    "category": "Customer Experience",
    "description": "Automated CRM insight generated based on recent customer behavior and transaction patterns.",
    "priority": 2,
    "recommendedAction": "Provide loyalty benefits to improve retention",
    "potentialRevenue": 41281.37,
    "riskExposure": 0.14,
    "generatedAt": "2024-02-24T14:00:00Z",
    "status": "Closed",
    "assignedTo": "Michael Brown",
    "relatedAlerts": []
  },
  {
    "id": 109,
    "customerId": 6128,
    "customerName": "Customer 6128",
    "insightType": "Cross-Sell Opportunity",
    "category": "Revenue Growth",
    "description": "Automated CRM insight generated based on recent customer behavior and transaction patterns.",
    "priority": 4,
    "recommendedAction": "Recommend credit card upgrade with higher limits",
    "potentialRevenue": 40956.43,
    "riskExposure": 0.67,
    "generatedAt": "2024-02-25T13:00:00Z",
    "status": "Closed",
    "assignedTo": "Priya Patel",
    "relatedAlerts": []
  },
  {
    "id": 110,
    "customerId": 4030,
    "customerName": "Customer 4030",
    "insightType": "Cross-Sell Opportunity",
    "category": "Customer Experience",
    "description": "Automated CRM insight generated based on recent customer behavior and transaction patterns.",
    "priority": 3,
    "recommendedAction": "Recommend credit card upgrade with higher limits",
    "potentialRevenue": 36858.02,
    "riskExposure": 0.75,
    "generatedAt": "2024-02-17T11:00:00Z",
    "status": "Closed",
    "assignedTo": "Sarah Johnson",
    "relatedAlerts": []
  },
  {
    "id": 111,
    "customerId": 3311,
    "customerName": "Customer 3311",
    "insightType": "Cross-Sell Opportunity",
    "category": "Customer Retention",
    "description": "Automated CRM insight generated based on recent customer behavior and transaction patterns.",
    "priority": 3,
    "recommendedAction": "Schedule personalized financial advisory session",
    "potentialRevenue": 17609.32,
    "riskExposure": 0.34,
    "generatedAt": "2024-02-04T16:00:00Z",
    "status": "Open",
    "assignedTo": "Amit Sharma",
    "relatedAlerts": []
  },
  {
    "id": 112,
    "customerId": 9231,
    "customerName": "Customer 9231",
    "insightType": "Retention Risk",
    "category": "Customer Retention",
    "description": "Automated CRM insight generated based on recent customer behavior and transaction patterns.",
    "priority": 1,
    "recommendedAction": "Offer digital banking feature walkthrough",
    "potentialRevenue": 27732.59,
    "riskExposure": 0.21,
    "generatedAt": "2024-02-16T21:00:00Z",
    "status": "In Progress",
    "assignedTo": "Michael Brown",
    "relatedAlerts": []
  },
  {
    "id": 113,
    "customerId": 9676,
    "customerName": "Customer 9676",
    "insightType": "Up-Sell Opportunity",
    "category": "Customer Experience",
    "description": "Automated CRM insight generated based on recent customer behavior and transaction patterns.",
    "priority": 4,
    "recommendedAction": "Provide loyalty benefits to improve retention",
    "potentialRevenue": 13989.61,
    "riskExposure": 0.21,
    "generatedAt": "2024-02-24T14:00:00Z",
    "status": "In Progress",
    "assignedTo": "Sarah Johnson",
    "relatedAlerts": []
  },
  {
    "id": 114,
    "customerId": 8296,
    "customerName": "Customer 8296",
    "insightType": "Customer Engagement",
    "category": "Revenue Growth",
    "description": "Automated CRM insight generated based on recent customer behavior and transaction patterns.",
    "priority": 5,
    "recommendedAction": "Schedule personalized financial advisory session",
    "potentialRevenue": 10620.92,
    "riskExposure": 0.9,
    "generatedAt": "2024-02-21T04:00:00Z",
    "status": "Closed",
    "assignedTo": "Michael Brown",
    "relatedAlerts": []
  },
  {
    "id": 115,
    "customerId": 4801,
    "customerName": "Customer 4801",
    "insightType": "Cross-Sell Opportunity",
    "category": "Customer Retention",
    "description": "Automated CRM insight generated based on recent customer behavior and transaction patterns.",
    "priority": 5,
    "recommendedAction": "Offer digital banking feature walkthrough",
    "potentialRevenue": 23577.98,
    "riskExposure": 0.32,
    "generatedAt": "2024-02-22T00:00:00Z",
    "status": "Closed",
    "assignedTo": "Michael Brown",
    "relatedAlerts": []
  },
  {
    "id": 116,
    "customerId": 2251,
    "customerName": "Customer 2251",
    "insightType": "Product Recommendation",
    "category": "Revenue Growth",
    "description": "Automated CRM insight generated based on recent customer behavior and transaction patterns.",
    "priority": 4,
    "recommendedAction": "Offer digital banking feature walkthrough",
    "potentialRevenue": 47215.69,
    "riskExposure": 0.07,
    "generatedAt": "2024-02-03T20:00:00Z",
    "status": "Closed",
    "assignedTo": "Emily Clark",
    "relatedAlerts": []
  },
  {
    "id": 117,
    "customerId": 5493,
    "customerName": "Customer 5493",
    "insightType": "Customer Engagement",
    "category": "Revenue Growth",
    "description": "Automated CRM insight generated based on recent customer behavior and transaction patterns.",
    "priority": 1,
    "recommendedAction": "Introduce bundled banking products",
    "potentialRevenue": 36433.6,
    "riskExposure": 0.25,
    "generatedAt": "2024-02-20T12:00:00Z",
    "status": "Closed",
    "assignedTo": "Sarah Johnson",
    "relatedAlerts": []
  },
  {
    "id": 118,
    "customerId": 8202,
    "customerName": "Customer 8202",
    "insightType": "Product Recommendation",
    "category": "Risk Mitigation",
    "description": "Automated CRM insight generated based on recent customer behavior and transaction patterns.",
    "priority": 3,
    "recommendedAction": "Provide loyalty benefits to improve retention",
    "potentialRevenue": 47815.69,
    "riskExposure": 0.5,
    "generatedAt": "2024-02-03T03:00:00Z",
    "status": "In Progress",
    "assignedTo": "Amit Sharma",
    "relatedAlerts": []
  },
  {
    "id": 119,
    "customerId": 2909,
    "customerName": "Customer 2909",
    "insightType": "Retention Risk",
    "category": "Customer Experience",
    "description": "Automated CRM insight generated based on recent customer behavior and transaction patterns.",
    "priority": 5,
    "recommendedAction": "Schedule personalized financial advisory session",
    "potentialRevenue": 42572.9,
    "riskExposure": 0.2,
    "generatedAt": "2024-02-15T02:00:00Z",
    "status": "Closed",
    "assignedTo": "Sarah Johnson",
    "relatedAlerts": []
  },
  {
    "id": 120,
    "customerId": 9237,
    "customerName": "Customer 9237",
    "insightType": "Customer Engagement",
    "category": "Customer Retention",
    "description": "Automated CRM insight generated based on recent customer behavior and transaction patterns.",
    "priority": 5,
    "recommendedAction": "Provide loyalty benefits to improve retention",
    "potentialRevenue": 28297.41,
    "riskExposure": 0.18,
    "generatedAt": "2024-02-17T16:00:00Z",
    "status": "Closed",
    "assignedTo": "Emily Clark",
    "relatedAlerts": []
  }
]